{
    "driveDisplayName": "FEATHERBOOT",
    "visual": {
      "image": "pkg://board.svg",
      "outlineImage": "pkg://boardwireframe.svg",
      "useCrocClips": false,
      "width": 454.7699890136719,
      "height": 204.60595703125,
      "pinDist": 15,
      "pinBlocks": [
        {
          "x": 391.94581559475085,
          "y": 187.25030517578128,
          "labels": [
            "D4"
          ]
        },
        {
          "x": 369.21187221487224,
          "y": 187.25030517578128,
          "labels": [
            "TX_D1"
          ]
        },
        {
          "x": 346.4779288349936,
          "y": 187.25030517578128,
          "labels": [
            "RX_D0"
          ]
        },
        {
          "x": 323.74401597260527,
          "y": 187.25030517578128,
          "labels": [
            "MISO"
          ]
        },
        {
          "x": 301.00854671821054,
          "y": 187.25030517578128,
          "labels": [
            "MOSI"
          ]
        },
        {
          "x": 278.27457282084157,
          "y": 187.25030517578128,
          "labels": [
            "SCK"
          ]
        },
        {
          "x": 255.54065995845326,
          "y": 187.25030517578128,
          "labels": [
            "A5"
          ]
        },
        {
          "x": 232.80673183731972,
          "y": 187.25030517578128,
          "labels": [
            "A4"
          ]
        },
        {
          "x": 210.0734140659927,
          "y": 187.25030517578128,
          "labels": [
            "A3"
          ]
        },
        {
          "x": 187.3394859448592,
          "y": 187.25030517578128,
          "labels": [
            "A2"
          ]
        },
        {
          "x": 164.60554256498057,
          "y": 187.25030517578128,
          "labels": [
            "A1"
          ]
        },
        {
          "x": 141.87162970259223,
          "y": 187.25030517578128,
          "labels": [
            "A0"
          ]
        },
        {
          "x": 119.1377092108313,
          "y": 187.25030517578128,
          "labels": [
            "GND"
          ]
        },
        {
          "x": 96.4037887190704,
          "y": 187.25030517578128,
          "labels": [
            "AREF"
          ]
        },
        {
          "x": 73.66984533919177,
          "y": 187.25030517578128,
          "labels": [
            "+3V3"
          ]
        },
        {
          "x": 141.87162970259223,
          "y": 5.37829732894897,
          "labels": [
            "VBAT"
          ]
        },
        {
          "x": 164.60554256498057,
          "y": 5.37829732894897,
          "labels": [
            "EN"
          ]
        },
        {
          "x": 187.3394859448592,
          "y": 5.37829732894897,
          "labels": [
            "VBUS"
          ]
        },
        {
          "x": 210.0734140659927,
          "y": 5.37829732894897,
          "labels": [
            "D13"
          ]
        },
        {
          "x": 232.80673183731972,
          "y": 5.37829732894897,
          "labels": [
            "D12"
          ]
        },
        {
          "x": 255.54065995845326,
          "y": 5.37829732894897,
          "labels": [
            "D11"
          ]
        },
        {
          "x": 278.27457282084157,
          "y": 5.37829732894897,
          "labels": [
            "D10"
          ]
        },
        {
          "x": 301.00854671821054,
          "y": 5.37829732894897,
          "labels": [
            "D9"
          ]
        },
        {
          "x": 323.74401597260527,
          "y": 5.37829732894897,
          "labels": [
            "D6"
          ]
        },
        {
          "x": 346.4779288349936,
          "y": 5.37829732894897,
          "labels": [
            "D5"
          ]
        },
        {
          "x": 369.21187221487224,
          "y": 5.37829732894897,
          "labels": [
            "SCL"
          ]
        },
        {
          "x": 391.94581559475085,
          "y": 5.37829732894897,
          "labels": [
            "SDA"
          ]
        },
        {
          "x": 64.06715079970797,
          "y": 132.6402435302734,
          "labels": [
            "RESET"
          ]
        }
      ],
      "leds": [
        {
          "x": 27.282228178160295,
          "y": 148.9976806640625,
          "w": 11.186988115068395,
          "h": 11.18702030181885,
          "color": "#ff0000",
          "label": "RXLED"
        },
        {
          "x": 18.16860503122264,
          "y": 54.829639434814446,
          "w": 11.186988115068395,
          "h": 11.18702030181885,
          "color": "#ff0000",
          "label": "LED"
        },
        {
          "x": 131.99298075687798,
          "y": 134.26794433593747,
          "w": 31.325527678006168,
          "h": 31.325617806549417,
          "color": "neopixel",
          "label": "NEOPIXEL"
        }
      ],
      "reset": {
        "x": 50.93590195931312,
        "y": 187.25030517578128,
        "w": 11.977372040958853,
        "h": 11.977406501770021
      }
    },
    "gpioPinMap": {
      "D4": "D4",
      "TX_D1": "TX_D1",
      "RX_D0": "RX_D0",
      "MISO": "MISO",
      "MOSI": "MOSI",
      "SCK": "SCK",
      "A5": "A5",
      "A4": "A4",
      "A3": "A3",
      "JACK_TX": "A4",
      "A2": "A2",
      "A1": "A1",
      "A0": "A0",
      "GND": "GND",
      "AREF": "AREF",
      "+3V3": "+3V3",
      "!RESET": "!RESET",
      "VBAT": "VBAT",
      "EN": "EN",
      "VBUS": "VBUS",
      "D13": "D13",
      "D12": "D12",
      "D11": "D11",
      "D10": "D10",
      "D9": "D9",
      "D6": "D6",
      "D5": "D5",
      "SCL": "SCL",
      "SDA": "SDA",
      "RXLED": "RXLED",
      "LED": "LED",
      "NEOPIXEL": "NEOPIXEL",
      "RESET": "RESET"
    },
    "groundPins": [
      "GND"
    ],
    "threeVoltPins": [
      "+3V3"
    ],
    "spiPins": {
      "MOSI": "MOSI",
      "MISO": "MISO",
      "SCK": "SCK"
    },
    "i2cPins": {
      "SDA": "SDA",
      "SCL": "SCL"
    },
    "onboardComponents": ["pixel"],
    "marginWhenBreadboarding": [
      0,
      0,
      80,
      0
    ]
  }